ecoflux/__init__.py
ecoflux/constants/__init__.py
ecoflux/constants/constants.py
ecoflux/leaf/__init__.py
ecoflux/leaf/light_response.py
ecoflux/leaf/stom_cond.py
ecoflux/physchem/__init__.py
ecoflux/physchem/sat_vap.py
ecoflux/radtrans/__init__.py
ecoflux/radtrans/canopy_light.py
ecoflux/radtrans/solar_radiation.py
ecoflux/stats/__init__.py
ecoflux/stats/dists.py
ecoflux/stats/regressions.py
ecoflux/stats/summary.py
ecoflux/stats/timeseries.py
ecoflux-0.1.1.dist-info/AUTHORS.md
ecoflux-0.1.1.dist-info/LICENSE
ecoflux-0.1.1.dist-info/METADATA
ecoflux-0.1.1.dist-info/WHEEL
ecoflux-0.1.1.dist-info/top_level.txt
ecoflux-0.1.1.dist-info/RECORD
