Metadata-Version: 2.2
Name: ecoflux
Version: 0.1.1
Summary: A library of functions to calculate ecosystem–atmosphere exchanges of energy, carbon, water, and trace gases
Home-page: https://github.com/wusunlab/ecoflux
Author: Wu Sun
Author-email: wusun@protonmail.com
License: mit
Project-URL: Documentation, https://github.com/wusunlab/ecoflux
Platform: any
Classifier: Development Status :: 1 - Planning
Classifier: Environment :: Console
Classifier: Intended Audience :: Science/Research
Classifier: Natural Language :: English
Classifier: License :: OSI Approved :: MIT License
Classifier: Programming Language :: Python
Classifier: Programming Language :: Python :: 3
Classifier: Programming Language :: Python :: Implementation :: CPython
Classifier: Topic :: Scientific/Engineering :: Atmospheric Science
License-File: LICENSE
License-File: AUTHORS.md
Requires-Dist: importlib-metadata; python_version < "3.8"
Requires-Dist: numpy
Requires-Dist: scipy
Provides-Extra: testing
Requires-Dist: pytest; extra == "testing"
Requires-Dist: pytest-cov; extra == "testing"
